pymongosql/__init__.py
pymongosql/common.py
pymongosql/connection.py
pymongosql/cursor.py
pymongosql/error.py
pymongosql/executor.py
pymongosql/helper.py
pymongosql/result_set.py
pymongosql/sql/__init__.py
pymongosql/sql/ast.py
pymongosql/sql/builder.py
pymongosql/sql/delete_builder.py
pymongosql/sql/delete_handler.py
pymongosql/sql/handler.py
pymongosql/sql/insert_builder.py
pymongosql/sql/insert_handler.py
pymongosql/sql/parser.py
pymongosql/sql/query_builder.py
pymongosql/sql/query_handler.py
pymongosql/sql/update_builder.py
pymongosql/sql/update_handler.py
pymongosql/sql/partiql/PartiQLLexer.g4
pymongosql/sql/partiql/PartiQLLexer.py
pymongosql/sql/partiql/PartiQLParser.g4
pymongosql/sql/partiql/PartiQLParser.py
pymongosql/sql/partiql/PartiQLParserListener.py
pymongosql/sql/partiql/PartiQLParserVisitor.py
pymongosql/sql/partiql/__init__.py
pymongosql/sqlalchemy_mongodb/__init__.py
pymongosql/sqlalchemy_mongodb/sqlalchemy_compat.py
pymongosql/sqlalchemy_mongodb/sqlalchemy_dialect.py
pymongosql/superset_mongodb/__init__.py
pymongosql/superset_mongodb/detector.py
pymongosql/superset_mongodb/executor.py
pymongosql/superset_mongodb/query_db.py
pymongosql/superset_mongodb/query_db_sqlite.py
pymongosql-0.3.4.dist-info/licenses/LICENSE
pymongosql-0.3.4.dist-info/METADATA
pymongosql-0.3.4.dist-info/WHEEL
pymongosql-0.3.4.dist-info/entry_points.txt
pymongosql-0.3.4.dist-info/top_level.txt
pymongosql-0.3.4.dist-info/RECORD
