Metadata-Version: 2.4
Name: pymongosql
Version: 0.3.4
Summary: Python DB API 2.0 (PEP 249) client for MongoDB
Author-email: Peng Ren <passren9099@hotmail.com>
Maintainer-email: Peng Ren <passren9099@hotmail.com>
License: MIT License
Project-URL: Homepage, https://github.com/passren/PyMongoSQL
Project-URL: Repository, https://github.com/passren/PyMongoSQL.git
Project-URL: Documentation, https://github.com/passren/PyMongoSQL/wiki
Project-URL: Bug Reports, https://github.com/passren/PyMongoSQL/issues
Keywords: mongodb,sql,database,dbapi,nosql
Classifier: Development Status :: 3 - Alpha
Classifier: Intended Audience :: Developers
Classifier: License :: OSI Approved :: MIT License
Classifier: Operating System :: OS Independent
Classifier: Programming Language :: Python :: 3
Classifier: Programming Language :: Python :: 3.9
Classifier: Programming Language :: Python :: 3.10
Classifier: Programming Language :: Python :: 3.11
Classifier: Programming Language :: Python :: 3.12
Classifier: Programming Language :: Python :: 3.13
Classifier: Topic :: Database
Classifier: Topic :: Database :: Database Engines/Servers
Classifier: Topic :: Software Development :: Libraries :: Python Modules
Requires-Python: >=3.9
License-File: LICENSE
Requires-Dist: pymongo>=4.15.0
Requires-Dist: antlr4-python3-runtime>=4.13.0
Requires-Dist: jmespath>=1.0.0
Provides-Extra: sqlalchemy
Requires-Dist: sqlalchemy>=1.4.0; extra == "sqlalchemy"
Provides-Extra: dev
Requires-Dist: pytest>=7.0.0; extra == "dev"
Requires-Dist: pytest-cov>=4.0.0; extra == "dev"
Requires-Dist: flake8>=6.0.0; extra == "dev"
Requires-Dist: flake8-pyproject>=1.2.0; extra == "dev"
Requires-Dist: black>=23.0.0; extra == "dev"
Requires-Dist: isort>=5.12.0; extra == "dev"
Dynamic: license-file
